{
  "preset": true,
  "txt-primary": "#fff",
  "bg-overlay": "#888888F0",
  "bg-secondary": "#929292F0",
  "bg-topbar": "#03a9f3",
  "bg-sidebar": "#fff",
  "bg-footer": "#fff",
  "bg-card": "#fff",
  "bg-card-header": "#03a9f3",
  "bg-page-title": "#6a6a6a",
  "bg-preloader": "#121212",
  "txt-page-title": "#fff",
  "txt-topbar": "#fff",
  "txt-sidebar": "#8d97ad",
  "txt-footer": "#000",
  "txt-card": "#000",
  "txt-card-header": "#fff",
  "txt-overlay": "#fff",
  "txt-secondary": "#fff",
  "hover-color": "#03a9f3",
  "overlay-blur": "0px",
  "border-radius": "0px",
  "bg": "#edf1f5"
}
